README.md
setup.cfg
setup.py
sensorpad/__init__.py
sensorpad/constants.py
sensorpad/settings.py
sensorpad/wrapper.py
sensorpad.egg-info/PKG-INFO
sensorpad.egg-info/SOURCES.txt
sensorpad.egg-info/dependency_links.txt
sensorpad.egg-info/top_level.txt
sensorpad/helpers/__init__.py
sensorpad/helpers/exceptions.py
sensorpad/helpers/parsers.py
sensorpad/helpers/simple_requests.py